LICENSE
README.md
novaad/__init__.py
novaad/__main__.py
novaad/core.py
novaad/gui.py
novaad-0.1.6.dist-info/LICENSE
novaad-0.1.6.dist-info/METADATA
novaad-0.1.6.dist-info/WHEEL
novaad-0.1.6.dist-info/entry_points.txt
novaad-0.1.6.dist-info/RECORD
