Metadata-Version: 2.1
Name: novaad
Version: 0.1.6
Summary: An Analog/Mixed-Signal IC design tool based on the Gm/Id method.
License: BSD-2
Keywords: analog,mixed-signal,ic,design,gm/id,eda-cad
Author: dasdias
Author-email: das.dias@campus.fct.unl.pt
Requires-Python: >=3.11,<4.0
Classifier: License :: Other/Proprietary License
Classifier: Programming Language :: Python :: 3
Classifier: Programming Language :: Python :: 3.11
Requires-Dist: PyYAML (>=6.0.2,<7.0.0)
Requires-Dist: confz (>=2.0.1,<3.0.0)
Requires-Dist: docopt (>=0.6.2,<0.7.0)
Requires-Dist: numpy (>=2.1.0,<3.0.0)
Requires-Dist: pandas (>=2.2.2,<3.0.0)
Requires-Dist: plotly (>=5.24.0,<6.0.0)
Requires-Dist: pydantic (>=2.8.2,<3.0.0)
Requires-Dist: scipy (>=1.14.1,<2.0.0)
Requires-Dist: tables (>=3.10.1,<4.0.0)
Requires-Dist: toml (>=0.10.2,<0.11.0)
